Workbook

Sheet sales_order_tracking_data
A1: Invoice_Number | B1: Invoice_Date | C1: Region | D1: Branch | E1: Sales_Channel | F1: Sales_Executive | G1: Customer_Name | H1: Product_Category | I1: Product_Name | J1: Quantity | K1: Unit_Price | L1: Gross_Sales | M1: Discount_Amount | N1: Return_Amount | O1: Net_Sales | P1: Order_Status | Q1: Payment_Status
A2: INV-2026-00001 | B2: 46038 | C2: East | D2: Guwahati | E2: Direct Sales | F2: Anita Desai | G2: Urban Store | H2: Stationery | I2: Notebook | J2: 1 | K2: 46265.74 | L2: 46265.74 | M2: 32.98 | N2: 0 | O2: 46232.76 | P2: Completed | Q2: Paid
A3: INV-2026-00002 | B3: 45966 | C3: East | D3: Bhubaneswar | E3: Direct Sales | F3: Anita Desai | G3: Skyline Corp | H3: Stationery | I3: File Folder | J3: 30 | K3: 34151.27 | L3: 1024538.1 | M3: 0 | N3: 0 | O3: 1024538.1 | P3: Cancelled | Q3: Pending
A4: INV-2026-00003 | B4: 46020 | C4: East | D4: Kolkata | E4: Retail Store | F4: Priya Patel | G4: Prime Retail | H4: Furniture | I4: Cabinet | J4: 48 | K4: 40373.07 | L4: 1937907.4 | M4: 233252.17 | N4: 0 | O4: 1704655.2 | P4: Completed | Q4: Paid
A5: INV-2026-00004 | B5: 46045 | C5: East | D5: Bhubaneswar | E5: Online | F5: Amit Kumar | G5: Nexus Ltd | H5: Sports Equipment | I5: Cricket Bat | J5: 21 | K5: 14989.13 | L5: 314771.73 | M5: 0 | N5: 0 | O5: 314771.73 | P5: Completed | Q5: Paid
A6: INV-2026-00005 | B6: 46027 | C6: South | D6: Hyderabad | E6: Distributor | F6: Rajesh Verma | G6: Future Tech | H6: Stationery | I6: Desk Organizer | J6: 40 | K6: 22865.77 | L6: 914630.8 | M6: 108718.05 | N6: 0 | O6: 805912.75 | P6: Cancelled | Q6: Pending
A7: INV-2026-00006 | B7: 46040 | C7: Central | D7: Bhopal | E7: Direct Sales | F7: Priya Patel | G7: Omega Stores | H7: Electronics | I7: Headphones | J7: 35 | K7: 6211.86 | L7: 217415.1 | M7: 0 | N7: 0 | O7: 217415.1 | P7: Completed | Q7: Paid
A8: INV-2026-00007 | B8: 45979 | C8: West | D8: Pune | E8: Online | F8: Sneha Reddy | G8: Smart Systems | H8: Furniture | I8: Cabinet | J8: 46 | K8: 20624.28 | L8: 948716.88 | M8: 133776.12 | N8: 0 | O8: 814940.76 | P8: Cancelled | Q8: Pending
A9: INV-2026-00008 | B9: 46024 | C9: West | D9: Surat | E9: Distributor | F9: Sneha Reddy | G9: Elite Enterprises | H9: Clothing | I9: Formal Shirt | J9: 37 | K9: 10597.89 | L9: 392121.93 | M9: 0 | N9: 0 | O9: 392121.93 | P9: Pending | Q9: Pending
A10: INV-2026-00009 | B10: 45980 | C10: Central | D10: Indore | E10: Direct Sales | F10: Suresh Gupta | G10: Future Tech | H10: Electronics | I10: Tablet | J10: 18 | K10: 30923.14 | L10: 556616.52 | M10: 0 | N10: 63437.49 | O10: 493179.03 | P10: Processing | Q10: Paid
A11: INV-2026-00010 | B11: 46007 | C11: East | D11: Patna | E11: Retail Store | F11: Sneha Reddy | G11: Smart Systems | H11: Stationery | I11: Desk Organizer | J11: 2 | K11: 16277.16 | L11: 32554.32 | M11: 3619.01 | N11: 0 | O11: 28935.31 | P11: Processing | Q11: Pending
A12: INV-2026-00011 | B12: 46002 | C12: Central | D12: Bhopal | E12: Distributor | F12: Amit Kumar | G12: Prime Retail | H12: Clothing | I12: Dress | J12: 15 | K12: 42354.93 | L12: 635323.95 | M12: 5670.76 | N12: 4182.74 | O12: 625470.45 | P12: Processing | Q12: Pending
A13: INV-2026-00012 | B13: 45966 | C13: North | D13: Jaipur | E13: Distributor | F13: Amit Kumar | G13: Metro Mart | H13: Furniture | I13: Office Chair | J13: 23 | K13: 49392.26 | L13: 1136022 | M13: 188661.91 | N13: 0 | O13: 947360.07 | P13: Pending | Q13: Pending
... A3501: INV-2026-03500 | B3501: 46043 | C3501: West | D3501: Pune | E3501: Distributor | F3501: Rahul Sharma | G3501: Nexus Ltd | H3501: Furniture | I3501: Office Chair | J3501: 1 | K3501: 29674.46 | L3501: 29674.46 | M3501: 3091.94 | N3501: 0 | O3501: 26582.52 | P3501: Cancelled | Q3501: Pending
L3504: =SUMIF(sales_order_tracking_data[Invoice_Date],TODAY()-1,sales_order_tracking_data[Gross_Sales]) -> 0
O3506: =TODAY()-1 -> 46046

Sheet TARGET
B3: Date/Month | C3: Region | D3: Branch | E3: Sales_Channel | F3: Product_Category | G3: Target_Value
B4: 46023 | C4: EAST | D4: Delhi | E4: Direct Sales | F4: Clothing | G4: 155000000
B5: 46023 | C5: WEST | D5: Mumbai | E5: Distributor | F5: Electronic | G5: 180000000
B6: 46023 | C6: NORTH | D6: Kolkata | E6: Online | F6: Furniture | G6: 72500000
B7: 46023 | C7: SOUTH | D7: Bangalore | E7: Retail Store | F7: stationery | G7: 125000000

Sheet REPORTS
W1: Invoice_Date | X1: 46045
C3: 46045 | W3: Row Labels | X3: Sum of Quantity | Y3: Sum of Net_Sales
C4: Overall Sale Snapshot | W4: Clothing | X4: 162 | Y4: 2949909.6
C5: Particulars | D5: Yesterday | E5: MTD | W5: Electronics | X5: 213 | Y5: 5790268.5
C6: Gross Sales | D6: =SUMIF(sales_order_tracking_data[Invoice_Date],C3,sales_order_tracking_data[Gross_Sales]) -> 28609797 | E6: =SUMIFS(sales_order_tracking_data[Gross_Sales],sales_order_tracking_data[Invoice_Date],">="&DATE(2026,1,1),sales_order_tracking_data[Invoice_Date],"<="&DATE(2026,1,31)) -> 5.5473264e+08 | W6: Furniture | X6: 195 | Y6: 3506741.9
C7: Sales Return | D7: =SUMIF(sales_order_tracking_data[Invoice_Date],C3,sales_order_tracking_data[Return_Amount]) -> 1061245.6 | E7: =SUMIFS(sales_order_tracking_data[Return_Amount],sales_order_tracking_data[Invoice_Date],">="&DATE(2026,1,1),sales_order_tracking_data[Invoice_Date],"<="&DATE(2026,1,31)) -> 12548927 | W7: Home Appliances | X7: 126 | Y7: 2358127
C8: Net Sales | D8: =SUMIF(sales_order_tracking_data[Invoice_Date],C3,sales_order_tracking_data[Net_Sales]) -> 25379535 | E8: =SUMIFS(sales_order_tracking_data[Net_Sales],sales_order_tracking_data[Invoice_Date],">="&DATE(2026,1,1),sales_order_tracking_data[Invoice_Date],"<="&DATE(2026,1,31)) -> 5.0612951e+08 | W8: Sports Equipment | X8: 257 | Y8: 6773566.4
C9: Target | D9: =SUM(TARGET!G4:G7)/30 -> 17750000 | E9: =SUM(TARGET!G4:G7) -> 532500000 | W9: Stationery | X9: 188 | Y9: 4000922
C10: Achievment (%) | D10: =D8/D9 -> 1.429833 | E10: =E8/E9 -> 0.95047795 | W10: Grand Total | X10: 1141 | Y10: 25379535
C14: 46045
C15: Region / Branch Wise Sales
C16: Region / Branch | D16: Yesterday Sales | E16: MTD Sales | F16: Target | G16: Variance | H16: Contribution
C17: EAST | D17: =SUMIFS(sales_order_tracking_data[Net_Sales],sales_order_tracking_data[Region],"EAST",sales_order_tracking_data[Invoice_Date],$C$14) -> 4297934.7 | E17: =SUMIFS(sales_order_tracking_data[Gross_Sales], sales_order_tracking_data[Invoice_Date], ">="&DATE(2026,1,1), sales_order_tracking_data[Invoice_Date], "<="&DATE(2026,1,31),sales_order_tracking_data[Region],"EAST") -> 1.0537387e+08 | F17: =VLOOKUP(C17,TARGET!$C$3:$G$7,5,FALSE) -> 155000000 | G17: =F17-E17 -> 49626133 | H17: =E17/$E$21 -> 0.23759233
C18: WEST | D18: =SUMIFS(sales_order_tracking_data[Net_Sales],sales_order_tracking_data[Region],"WEST",sales_order_tracking_data[Invoice_Date],$C$14) -> 5994574 | E18: =SUMIFS(sales_order_tracking_data[Gross_Sales], sales_order_tracking_data[Invoice_Date], ">="&DATE(2026,1,1), sales_order_tracking_data[Invoice_Date], "<="&DATE(2026,1,31),sales_order_tracking_data[Region],C18) -> 1.088303e+08 | F18: =VLOOKUP(C18,TARGET!$C$3:$G$7,5,FALSE) -> 180000000 | G18: =F18-E18 -> 71169702 | H18: =E18/$E$21 -> 0.24538574
C19: NORTH | D19: =SUMIFS(sales_order_tracking_data[Net_Sales],sales_order_tracking_data[Region],"NORTH",sales_order_tracking_data[Invoice_Date],$C$14) -> 3841943.4 | E19: =SUMIFS(sales_order_tracking_data[Gross_Sales], sales_order_tracking_data[Invoice_Date], ">="&DATE(2026,1,1), sales_order_tracking_data[Invoice_Date], "<="&DATE(2026,1,31),sales_order_tracking_data[Region],C19) -> 1.176517e+08 | F19: =VLOOKUP(C19,TARGET!$C$3:$G$7,5,FALSE) -> 72500000 | G19: =F19-E19 -> -45151703 | H19: =E19/$E$21 -> 0.26527585
C20: SOUTH | D20: =SUMIFS(sales_order_tracking_data[Net_Sales],sales_order_tracking_data[Region],"SOUTH",sales_order_tracking_data[Invoice_Date],$C$14) -> 5494611.2 | E20: =SUMIFS(sales_order_tracking_data[Gross_Sales], sales_order_tracking_data[Invoice_Date], ">="&DATE(2026,1,1), sales_order_tracking_data[Invoice_Date], "<="&DATE(2026,1,31),sales_order_tracking_data[Region],C20) -> 1.1165115e+08 | F20: =VLOOKUP(C20,TARGET!$C$3:$G$7,5,FALSE) -> 125000000 | G20: =F20-E20 -> 13348846 | H20: =E20/$E$21 -> 0.25174608
C21: Total | D21: =SUM(D17:D20) -> 19629063 | E21: =SUM(E17:E20) -> 4.4350702e+08 | F21: =SUM(F17:F20) -> 532500000 | H21: 1
C27: Channel Wise Sales
C28: Sales Channel | D28: Yesterday | E28: MTD | F28: % Share
C29: Online | D29: =SUMIFS(sales_order_tracking_data[Net_Sales],sales_order_tracking_data[Invoice_Date],$C$3,sales_order_tracking_data[Sales_Channel],C29) -> 9564642.4 | E29: =SUMIFS(sales_order_tracking_data[Net_Sales],sales_order_tracking_data[Invoice_Date],">="&DATE(2026,1,1),sales_order_tracking_data[Invoice_Date],"<="&DATE(2026,1,31),sales_order_tracking_data[Sales_Channel],C29) -> 1.2047957e+08 | F29: =E29/$E$33 -> 0.23804099
C30: Retail Store | D30: =SUMIFS(sales_order_tracking_data[Net_Sales],sales_order_tracking_data[Invoice_Date],$C$3,sales_order_tracking_data[Sales_Channel],C30) -> 4400555.3 | E30: =SUMIFS(sales_order_tracking_data[Net_Sales],sales_order_tracking_data[Invoice_Date],">="&DATE(2026,1,1),sales_order_tracking_data[Invoice_Date],"<="&DATE(2026,1,31),sales_order_tracking_data[Sales_Channel],C30) -> 1.1336436e+08 | F30: =E30/$E$33 -> 0.22398291
C31: Distributor | D31: =SUMIFS(sales_order_tracking_data[Net_Sales],sales_order_tracking_data[Invoice_Date],$C$3,sales_order_tracking_data[Sales_Channel],C31) -> 5792820.5 | E31: =SUMIFS(sales_order_tracking_data[Net_Sales],sales_order_tracking_data[Invoice_Date],">="&DATE(2026,1,1),sales_order_tracking_data[Invoice_Date],"<="&DATE(2026,1,31),sales_order_tracking_data[Sales_Channel],C31) -> 1.4097085e+08 | F31: =E31/$E$33 -> 0.27852723
C32: Direct Sales | D32: =SUMIFS(sales_order_tracking_data[Net_Sales],sales_order_tracking_data[Invoice_Date],$C$3,sales_order_tracking_data[Sales_Channel],C32) -> 5621517.1 | E32: =SUMIFS(sales_order_tracking_data[Net_Sales],sales_order_tracking_data[Invoice_Date],">="&DATE(2026,1,1),sales_order_tracking_data[Invoice_Date],"<="&DATE(2026,1,31),sales_order_tracking_data[Sales_Channel],C32) -> 1.3131473e+08 | F32: =E32/$E$33 -> 0.25944887
C33: Total | D33: =SUM(D29:D32) -> 25379535 | E33: =SUM(E29:E32) -> 5.0612951e+08 | F33: =SUM(F29:F32) -> 1
C38: Product / Category Wise Sales
C39: Product / Category | D39: QTY Sold | E39: Sales Value | F39: MTD Sales | G39: Margin
C40: Clothing | D40: =SUMIFS(sales_order_tracking_data[Quantity],sales_order_tracking_data[Product_Category],$C40) -> 13776 | E40: =SUMIFS(sales_order_tracking_data[Net_Sales],sales_order_tracking_data[Product_Category],C40) -> 3.0125998e+08 | F40: =SUMIFS(sales_order_tracking_data[Net_Sales],sales_order_tracking_data[Invoice_Date],">="&DATE(2026,1,1),sales_order_tracking_data[Invoice_Date],"<="&DATE(2026,1,31),sales_order_tracking_data[Product_Category],C40) -> 65595447 | G40: =+F40/$F$46 -> 0.1296021
C41: ElectronicS | D41: =SUMIFS(sales_order_tracking_data[Quantity],sales_order_tracking_data[Product_Category],$C41) -> 14926 | E41: =SUMIFS(sales_order_tracking_data[Net_Sales],sales_order_tracking_data[Product_Category],C41) -> 3.5436651e+08 | F41: =SUMIFS(sales_order_tracking_data[Net_Sales],sales_order_tracking_data[Invoice_Date],">="&DATE(2026,1,1),sales_order_tracking_data[Invoice_Date],"<="&DATE(2026,1,31),sales_order_tracking_data[Product_Category],C41) -> 85140544 | G41: =+F41/$F$46 -> 0.16821889
C42: Furniture | D42: =SUMIFS(sales_order_tracking_data[Quantity],sales_order_tracking_data[Product_Category],$C42) -> 15151 | E42: =SUMIFS(sales_order_tracking_data[Net_Sales],sales_order_tracking_data[Product_Category],C42) -> 3.6219507e+08 | F42: =SUMIFS(sales_order_tracking_data[Net_Sales],sales_order_tracking_data[Invoice_Date],">="&DATE(2026,1,1),sales_order_tracking_data[Invoice_Date],"<="&DATE(2026,1,31),sales_order_tracking_data[Product_Category],C42) -> 92893076 | G42: =+F42/$F$46 -> 0.18353618
C43: Home Appliances | D43: =SUMIFS(sales_order_tracking_data[Quantity],sales_order_tracking_data[Product_Category],$C43) -> 14955 | E43: =SUMIFS(sales_order_tracking_data[Net_Sales],sales_order_tracking_data[Product_Category],C43) -> 3.3266556e+08 | F43: =SUMIFS(sales_order_tracking_data[Net_Sales],sales_order_tracking_data[Invoice_Date],">="&DATE(2026,1,1),sales_order_tracking_data[Invoice_Date],"<="&DATE(2026,1,31),sales_order_tracking_data[Product_Category],C43) -> 91090346 | G43: =+F43/$F$46 -> 0.17997438
C44: Sports Equipment | D44: =SUMIFS(sales_order_tracking_data[Quantity],sales_order_tracking_data[Product_Category],$C44) -> 16011 | E44: =SUMIFS(sales_order_tracking_data[Net_Sales],sales_order_tracking_data[Product_Category],C44) -> 3.7993284e+08 | F44: =SUMIFS(sales_order_tracking_data[Net_Sales],sales_order_tracking_data[Invoice_Date],">="&DATE(2026,1,1),sales_order_tracking_data[Invoice_Date],"<="&DATE(2026,1,31),sales_order_tracking_data[Product_Category],C44) -> 81933252 | G44: =+F44/$F$46 -> 0.16188199
C45: stationery | D45: =SUMIFS(sales_order_tracking_data[Quantity],sales_order_tracking_data[Product_Category],$C45) -> 14915 | E45: =SUMIFS(sales_order_tracking_data[Net_Sales],sales_order_tracking_data[Product_Category],C45) -> 3.3047435e+08 | F45: =SUMIFS(sales_order_tracking_data[Net_Sales],sales_order_tracking_data[Invoice_Date],">="&DATE(2026,1,1),sales_order_tracking_data[Invoice_Date],"<="&DATE(2026,1,31),sales_order_tracking_data[Product_Category],C45) -> 89476845 | G45: =+F45/$F$46 -> 0.17678646
C46: Total | D46: =SUM(D40:D45) -> 89734 | E46: =SUM(E40:E45) -> 2.0608943e+09 | F46: =SUM(F40:F45) -> 5.0612951e+08 | G46: =+F46/$F$46 -> 1
